sklearn/__init__.py
sklearn/datasets/__init__.py
sklearn/datasets/make_regression.py
sklearn_testing_demo-0.1.dist-info/METADATA
sklearn_testing_demo-0.1.dist-info/WHEEL
sklearn_testing_demo-0.1.dist-info/top_level.txt
sklearn_testing_demo-0.1.dist-info/RECORD
